classification/__init__.py
classification/classification_.py
classification/classification_combined.py
classification/logging_util.py
instance_seg/__init__.py
instance_seg/augment_poly.py
instance_seg/json_reader_poly.py
instance_seg/logging_util.py
instance_seg/utils_poly.py
instance_seg/yml_writer_poly.py
object_detection_new/__init__.py
object_detection_new/augmentation_rect.py
object_detection_new/logging_util.py
object_detection_new/txt_reader_rect.py
object_detection_new/utils_poly.py
object_detection_new/yml_writer_poly.py
image_augs-2.4.20.dist-info/METADATA
image_augs-2.4.20.dist-info/WHEEL
image_augs-2.4.20.dist-info/top_level.txt
image_augs-2.4.20.dist-info/RECORD
