Metadata-Version: 2.1
Name: image-augs
Version: 2.4.20
Summary: Image Augs supports Augmentation for Object Detection , Instance Segmentation and classification tasks.
Author: Souvik Saha
Author-email: ssouvik.191@gmail.com
Keywords: machine_learning,development,data_augmentations
Classifier: Intended Audience :: Developers
Classifier: Operating System :: OS Independent
Classifier: Programming Language :: Python
Classifier: Programming Language :: Python :: 3.8
Classifier: License :: OSI Approved :: MIT License
Requires-Python: >=3.7
Requires-Dist: opencv-contrib-python
Requires-Dist: opencv-python
Requires-Dist: albumentations ==1.3.0
Requires-Dist: tqdm
Requires-Dist: tornado
Requires-Dist: bbox-visualizer >=0.1.0
Requires-Dist: pybboxes >=0.1.5
Requires-Dist: scikit-image >=0.19.3
Requires-Dist: Pillow
Requires-Dist: matplotlib
Requires-Dist: rich >=12.6.0
Requires-Dist: imgaug >=0.4.0
Requires-Dist: labelme ==5.1.1
Requires-Dist: numpyencoder ==0.3.0
Requires-Dist: imagecorruptions ==1.1.2
Requires-Dist: PyQt5 ==5.15.7
Requires-Dist: PyQt5-Qt5 ==5.15.2
Requires-Dist: PyQt5-sip ==12.11.1
Requires-Dist: setuptools
Requires-Dist: wheel
Requires-Dist: numpy
Requires-Dist: seaborn
